libro_server/__init__.py
libro_server/_version.py
libro_server/app.py
libro_server/entrypoint.py
libro_server/generate_libro_config.py
libro_server/jupyter_config.py
libro_server/libro_ai_handler.py
libro_server/libro_kernel_manager.py
libro_server/static_handler.py
libro_server/workspace_handler.py
libro_server/static/113.c38af660.async.js
libro_server/static/221.62e42252.async.js
libro_server/static/332.5a49fa2c.chunk.css
libro_server/static/332.647e378b.async.js
libro_server/static/365.3a6bd261.chunk.css
libro_server/static/371.569f4c46.chunk.css
libro_server/static/371.cfe2dcb7.async.js
libro_server/static/881.1aab430c.async.js
libro_server/static/index.html
libro_server/static/p__dbgpt__index.b732b337.chunk.css
libro_server/static/p__dbgpt__index.e958215f.async.js
libro_server/static/p__execution__index.b3beadf1.chunk.css
libro_server/static/p__execution__index.d0f0acb6.async.js
libro_server/static/p__interaction__index.54256212.chunk.css
libro_server/static/p__interaction__index.d06f8360.async.js
libro_server/static/p__libro__index.1093a7c3.chunk.css
libro_server/static/p__libro__index.30d004f1.async.js
libro_server/static/preload_helper.ee7f9d88.js
libro_server/static/umi.e5d95163.js
libro_server/static/static/KaTeX_AMS-Regular.1608a09b.woff
libro_server/static/static/KaTeX_AMS-Regular.4aafdb68.ttf
libro_server/static/static/KaTeX_AMS-Regular.a79f1c31.woff2
libro_server/static/static/KaTeX_Caligraphic-Bold.b6770918.woff
libro_server/static/static/KaTeX_Caligraphic-Bold.cce5b8ec.ttf
libro_server/static/static/KaTeX_Caligraphic-Bold.ec17d132.woff2
libro_server/static/static/KaTeX_Caligraphic-Regular.07ef19e7.ttf
libro_server/static/static/KaTeX_Caligraphic-Regular.55fac258.woff2
libro_server/static/static/KaTeX_Caligraphic-Regular.dad44a7f.woff
libro_server/static/static/KaTeX_Fraktur-Bold.9f256b85.woff
libro_server/static/static/KaTeX_Fraktur-Bold.b18f59e1.ttf
libro_server/static/static/KaTeX_Fraktur-Bold.d42a5579.woff2
libro_server-0.1.10.dist-info/METADATA
libro_server-0.1.10.dist-info/WHEEL
libro_server-0.1.10.dist-info/entry_points.txt
libro_server-0.1.10.dist-info/RECORD
